djangocms_flexslider/__init__.py
djangocms_flexslider/apps.py
djangocms_flexslider/cms_plugins.py
djangocms_flexslider/forms.py
djangocms_flexslider/models.py
djangocms_flexslider/settings.py
djangocms_flexslider/locale/__init__.py
djangocms_flexslider/locale/de/LC_MESSAGES/django.po
djangocms_flexslider/locale/es/LC_MESSAGES/django.po
djangocms_flexslider/locale/fr/LC_MESSAGES/django.po
djangocms_flexslider/locale/hi/LC_MESSAGES/django.po
djangocms_flexslider/locale/it/LC_MESSAGES/django.po
djangocms_flexslider/locale/ml/LC_MESSAGES/django.po
djangocms_flexslider/locale/sk/LC_MESSAGES/django.po
djangocms_flexslider/locale/zh-hans/LC_MESSAGES/django.po
djangocms_flexslider/locale/zh-hant/LC_MESSAGES/django.po
djangocms_flexslider/migrations/0001_initial.py
djangocms_flexslider/migrations/__init__.py
djangocms_flexslider/templates/djangocms_flexslider/_slide.html
djangocms_flexslider/templates/djangocms_flexslider/_slider.html
djangocms_flexslider/tests/__init__.py
djangocms_flexslider/tests/test_models.py
djangocms_flexslider/tests/test_plugins.py
djangocms_flexslider/tests/test_settings.py
djangocms_flexslider/tests/media/avatar.png
djangocms_flexslider-1.0.0.dist-info/DESCRIPTION.rst
djangocms_flexslider-1.0.0.dist-info/METADATA
djangocms_flexslider-1.0.0.dist-info/RECORD
djangocms_flexslider-1.0.0.dist-info/WHEEL
djangocms_flexslider-1.0.0.dist-info/metadata.json
djangocms_flexslider-1.0.0.dist-info/top_level.txt
