Metadata-Version: 1.1
Name: djangocms-flexslider
Version: 1.0.0
Summary: A Django CMS image slider plugin that uses FlexSlider.
Home-page: https://github.com/tdsymonds/djangocms-flexslider
Author: Tom Symonds
Author-email: tdsymonds@hotmail.com
License: MIT License
Keywords: djangocms-flexslider,flexslider,django,image-slider
Platform: UNKNOWN
Classifier: Environment :: Web Environment
Classifier: Framework :: Django
Classifier: Framework :: Django :: 1.8
Classifier: Framework :: Django :: 1.9
Classifier: Intended Audience :: Developers
Classifier: License :: OSI Approved :: MIT License
Classifier: Operating System :: OS Independent
Classifier: Programming Language :: Python :: 2
Classifier: Programming Language :: Python :: 2.7
Classifier: Topic :: Internet :: WWW/HTTP
Classifier: Topic :: Internet :: WWW/HTTP :: Dynamic Content
